aiverify_general_corruptions/__init__.py
aiverify_general_corruptions/__main__.py
aiverify_general_corruptions/algo.meta.json
aiverify_general_corruptions/algo.py
aiverify_general_corruptions/algo_init.py
aiverify_general_corruptions/input.schema.json
aiverify_general_corruptions/output.schema.json
aiverify_general_corruptions/plugin_init.py
aiverify_general_corruptions/utils/general.py
aiverify_general_corruptions-2.1.0.dist-info/METADATA
aiverify_general_corruptions-2.1.0.dist-info/WHEEL
aiverify_general_corruptions-2.1.0.dist-info/entry_points.txt
aiverify_general_corruptions-2.1.0.dist-info/licenses/AUTHORS.rst
aiverify_general_corruptions-2.1.0.dist-info/licenses/LICENSE
aiverify_general_corruptions-2.1.0.dist-info/licenses/NOTICE.md
aiverify_general_corruptions-2.1.0.dist-info/RECORD
